odoo/addons/l10n_it_fatturapa_auto_sale_order/README.rst
odoo/addons/l10n_it_fatturapa_auto_sale_order/__init__.py
odoo/addons/l10n_it_fatturapa_auto_sale_order/__manifest__.py
odoo/addons/l10n_it_fatturapa_auto_sale_order/i18n/it.po
odoo/addons/l10n_it_fatturapa_auto_sale_order/i18n/l10n_it_fatturapa_auto_sale_order.pot
odoo/addons/l10n_it_fatturapa_auto_sale_order/models/__init__.py
odoo/addons/l10n_it_fatturapa_auto_sale_order/models/account_move.py
odoo/addons/l10n_it_fatturapa_auto_sale_order/readme/CONFIGURE.md
odoo/addons/l10n_it_fatturapa_auto_sale_order/readme/CONTRIBUTORS.md
odoo/addons/l10n_it_fatturapa_auto_sale_order/readme/DESCRIPTION.md
odoo/addons/l10n_it_fatturapa_auto_sale_order/readme/INSTALL.md
odoo/addons/l10n_it_fatturapa_auto_sale_order/readme/USAGE.md
odoo/addons/l10n_it_fatturapa_auto_sale_order/static/description/icon.png
odoo/addons/l10n_it_fatturapa_auto_sale_order/static/description/index.html
odoo/addons/l10n_it_fatturapa_auto_sale_order/tests/__init__.py
odoo/addons/l10n_it_fatturapa_auto_sale_order/tests/test_related_documents.py
odoo_addon_l10n_it_fatturapa_auto_sale_order-16.0.1.0.0.4.dist-info/METADATA
odoo_addon_l10n_it_fatturapa_auto_sale_order-16.0.1.0.0.4.dist-info/WHEEL
odoo_addon_l10n_it_fatturapa_auto_sale_order-16.0.1.0.0.4.dist-info/top_level.txt
odoo_addon_l10n_it_fatturapa_auto_sale_order-16.0.1.0.0.4.dist-info/RECORD
